adafruit_lis3dh.py
adafruit_circuitpython_lis3dh-5.2.8.dist-info/licenses/LICENSE
adafruit_circuitpython_lis3dh-5.2.8.dist-info/METADATA
adafruit_circuitpython_lis3dh-5.2.8.dist-info/WHEEL
adafruit_circuitpython_lis3dh-5.2.8.dist-info/top_level.txt
adafruit_circuitpython_lis3dh-5.2.8.dist-info/RECORD
